odoo/addons/stock_account_change_qty_reason/README.rst
odoo/addons/stock_account_change_qty_reason/__init__.py
odoo/addons/stock_account_change_qty_reason/__manifest__.py
odoo/addons/stock_account_change_qty_reason/i18n/it.po
odoo/addons/stock_account_change_qty_reason/i18n/stock_account_change_qty_reason.pot
odoo/addons/stock_account_change_qty_reason/i18n/zh_CN.po
odoo/addons/stock_account_change_qty_reason/models/__init__.py
odoo/addons/stock_account_change_qty_reason/models/stock_move.py
odoo/addons/stock_account_change_qty_reason/models/stock_quant_reason.py
odoo/addons/stock_account_change_qty_reason/readme/CONFIGURE.md
odoo/addons/stock_account_change_qty_reason/readme/CONTRIBUTORS.md
odoo/addons/stock_account_change_qty_reason/readme/DESCRIPTION.md
odoo/addons/stock_account_change_qty_reason/static/description/icon.png
odoo/addons/stock_account_change_qty_reason/static/description/index.html
odoo/addons/stock_account_change_qty_reason/tests/__init__.py
odoo/addons/stock_account_change_qty_reason/tests/test_stock_account_change_qty_reason.py
odoo/addons/stock_account_change_qty_reason/views/stock_move_line_view.xml
odoo/addons/stock_account_change_qty_reason/views/stock_quant_reason_view.xml
odoo_addon_stock_account_change_qty_reason-17.0.1.0.0.4.dist-info/METADATA
odoo_addon_stock_account_change_qty_reason-17.0.1.0.0.4.dist-info/WHEEL
odoo_addon_stock_account_change_qty_reason-17.0.1.0.0.4.dist-info/top_level.txt
odoo_addon_stock_account_change_qty_reason-17.0.1.0.0.4.dist-info/RECORD
